README.txt
setup.py
eqb/__init__.py
eqb.recipe.uwsgi.egg-info/PKG-INFO
eqb.recipe.uwsgi.egg-info/SOURCES.txt
eqb.recipe.uwsgi.egg-info/dependency_links.txt
eqb.recipe.uwsgi.egg-info/entry_points.txt
eqb.recipe.uwsgi.egg-info/not-zip-safe
eqb.recipe.uwsgi.egg-info/requires.txt
eqb.recipe.uwsgi.egg-info/top_level.txt
eqb/recipe/__init__.py
eqb/recipe/uwsgi/__init__.py