Metadata-Version: 1.0
Name: eqb.recipe.uwsgi
Version: 0.0.2
Summary:             this is a recipe to build a uwsgi binary as well as the xml config file.
